sphinx_combine/__init__.py
sphinx_combine/py.typed
sphinx_combine-2026.1.11.dist-info/licenses/LICENSE
sphinx_combine-2026.1.11.dist-info/METADATA
sphinx_combine-2026.1.11.dist-info/WHEEL
sphinx_combine-2026.1.11.dist-info/top_level.txt
sphinx_combine-2026.1.11.dist-info/RECORD
