Metadata-Version: 2.4
Name: sphinx-combine
Version: 2026.1.11
Summary: Extension for Sphinx which enables combining code blocks.
Author-email: Adam Dangoor <adamdangoor@gmail.com>
License:                                 Apache License
Project-URL: Source, https://github.com/adamtheturtle/sphinx-combine
Keywords: documentation,rst,sphinx
Classifier: Development Status :: 5 - Production/Stable
Classifier: Environment :: Web Environment
Classifier: Framework :: Pytest
Classifier: License :: OSI Approved :: MIT License
Classifier: Operating System :: Microsoft :: Windows
Classifier: Operating System :: POSIX
Classifier: Programming Language :: Python :: 3 :: Only
Classifier: Programming Language :: Python :: 3.11
Classifier: Programming Language :: Python :: 3.12
Classifier: Programming Language :: Python :: 3.13
Requires-Python: >=3.11
License-File: LICENSE
Requires-Dist: docutils>=0.19
Requires-Dist: sphinx>=8.2.3
Provides-Extra: dev
Requires-Dist: actionlint-py==1.7.10.24; extra == "dev"
Requires-Dist: beartype==0.22.9; extra == "dev"
Requires-Dist: check-manifest==0.51; extra == "dev"
Requires-Dist: deptry==0.24.0; extra == "dev"
Requires-Dist: doc8==2.0.0; extra == "dev"
Requires-Dist: doccmd==2026.1.3.2; extra == "dev"
Requires-Dist: docformatter==1.7.7; extra == "dev"
Requires-Dist: interrogate==1.7.0; extra == "dev"
Requires-Dist: mypy[faster-cache]==1.19.1; extra == "dev"
Requires-Dist: mypy-strict-kwargs==2025.4.3; extra == "dev"
Requires-Dist: myst-parser==4.0.1; extra == "dev"
Requires-Dist: prek==0.2.27; extra == "dev"
Requires-Dist: pyenchant==3.3.0; extra == "dev"
Requires-Dist: pylint==4.0.4; extra == "dev"
Requires-Dist: pyproject-fmt==2.11.1; extra == "dev"
Requires-Dist: pyrefly==0.47.0; extra == "dev"
Requires-Dist: pyright==1.1.408; extra == "dev"
Requires-Dist: pyroma==5.0.1; extra == "dev"
Requires-Dist: pytest==9.0.2; extra == "dev"
Requires-Dist: pytest-cov==7.0.0; extra == "dev"
Requires-Dist: ruff==0.14.11; extra == "dev"
Requires-Dist: shellcheck-py==0.11.0.1; extra == "dev"
Requires-Dist: shfmt-py==3.12.0.2; extra == "dev"
Requires-Dist: sphinx-lint==1.0.2; extra == "dev"
Requires-Dist: ty==0.0.11; extra == "dev"
Requires-Dist: types-docutils==0.22.3.20251115; extra == "dev"
Requires-Dist: vulture==2.14; extra == "dev"
Requires-Dist: yamlfix==1.19.1; extra == "dev"
Requires-Dist: zizmor==1.20.0; extra == "dev"
Provides-Extra: release
Requires-Dist: check-wheel-contents==0.6.3; extra == "release"
Dynamic: license-file
